pyams_zodb_browser/__init__.py
pyams_zodb_browser/btreesupport.py
pyams_zodb_browser/cache.py
pyams_zodb_browser/diff.py
pyams_zodb_browser/history.py
pyams_zodb_browser/include.py
pyams_zodb_browser/interfaces.py
pyams_zodb_browser/state.py
pyams_zodb_browser/value.py
pyams_zodb_browser/doctests/README.rst
pyams_zodb_browser/locales/pyams_zodb_browser.pot
pyams_zodb_browser/locales/fr/LC_MESSAGES/pyams_zodb_browser.po
pyams_zodb_browser/tests/__init__.py
pyams_zodb_browser/tests/test_utilsdocs.py
pyams_zodb_browser/tests/test_utilsdocstrings.py
pyams_zodb_browser/zmi/__init__.py
pyams_zodb_browser/zmi/views.py
pyams_zodb_browser/zmi/resources/css/zodbbrowser.css
pyams_zodb_browser/zmi/resources/css/zodbbrowser.min.css
pyams_zodb_browser/zmi/resources/img/collapse.png
pyams_zodb_browser/zmi/resources/img/expand.png
pyams_zodb_browser/zmi/resources/js/zodbbrowser.js
pyams_zodb_browser/zmi/resources/js/zodbbrowser.min.js
pyams_zodb_browser/zmi/templates/zodbhistory.pt
pyams_zodb_browser/zmi/templates/zodbinfo.pt
pyams_zodb_browser-2.1.0.dist-info/LICENSE
pyams_zodb_browser-2.1.0.dist-info/METADATA
pyams_zodb_browser-2.1.0.dist-info/WHEEL
pyams_zodb_browser-2.1.0.dist-info/entry_points.txt
pyams_zodb_browser-2.1.0.dist-info/namespace_packages.txt
pyams_zodb_browser-2.1.0.dist-info/top_level.txt
pyams_zodb_browser-2.1.0.dist-info/RECORD
