Metadata-Version: 2.1
Name: pyams-zodb-browser
Version: 2.1.0
Summary: PyAMS ZODB browser package
Home-page: https://pyams.readthedocs.io
Author: Thierry Florac
Author-email: tflorac@ulthar.net
License: ZPL
Keywords: Pyramid PyAMS
Classifier: License :: OSI Approved :: Zope Public License
Classifier: Development Status :: 4 - Beta
Classifier: Programming Language :: Python
Classifier: Framework :: Pyramid
Classifier: Topic :: Software Development :: Libraries :: Python Modules
License-File: LICENSE
Requires-Dist: setuptools
Requires-Dist: ZODB
Requires-Dist: fanstatic
Requires-Dist: persistent
Requires-Dist: pyams-layer
Requires-Dist: pyams-pagelet
Requires-Dist: pyams-security
Requires-Dist: pyams-site
Requires-Dist: pyams-skin
Requires-Dist: pyams-template
Requires-Dist: pyams-utils
Requires-Dist: pyams-viewlet
Requires-Dist: pyams-zmi
Requires-Dist: pyramid >=2.0.0
Requires-Dist: transaction
Requires-Dist: zope.component
Requires-Dist: zope.container
Requires-Dist: zope.exceptions
Requires-Dist: zope.interface
Requires-Dist: zope.traversing
Provides-Extra: test
Requires-Dist: cffi ; extra == 'test'
Requires-Dist: importlib-metadata ; extra == 'test'
Requires-Dist: pyramid-zcml ; extra == 'test'
Requires-Dist: zope.exceptions ; extra == 'test'
